ariston/__init__.py
ariston/ariston_api.py
ariston/base_device.py
ariston/bsb_device.py
ariston/const.py
ariston/device.py
ariston/evo_device.py
ariston/evo_lydos_device.py
ariston/evo_one_device.py
ariston/galevo_device.py
ariston/lux2_device.py
ariston/lux_device.py
ariston/lydos_hybrid_device.py
ariston/nuos_split_device.py
ariston/velis_base_device.py
ariston/velis_device.py
ariston-0.19.8.dist-info/LICENSE
ariston-0.19.8.dist-info/WHEEL
ariston-0.19.8.dist-info/METADATA
ariston-0.19.8.dist-info/RECORD
