Metadata-Version: 2.3
Name: ariston
Version: 0.19.8
Summary: Ariston module
Author-email: Tamás Füstös <fustom@gmail.com>
Requires-Python: >=3.9
Requires-Dist: aiohttp
Requires-Dist: requests
Project-URL: Issues, https://github.com/fustom/python-ariston-api/issues
Project-URL: Repository, https://github.com/fustom/python-ariston-api.git
